catadjust/__init__.py
catadjust/adjust_loss.py
catadjust/adjust_rate.py
catadjust/optimisers.py
catadjust/autoadjust/__init__.py
catadjust/autoadjust/adjust.py
catadjust/autoadjust/calcep.py
catadjust/autoadjust/rms.py
catadjust-0.6.4.dist-info/METADATA
catadjust-0.6.4.dist-info/WHEEL
catadjust-0.6.4.dist-info/licenses/LICENSE
catadjust-0.6.4.dist-info/RECORD
