Metadata-Version: 2.4
Name: catadjust
Version: 0.6.4
Summary: Adjustment tools for catastrophe models
Project-URL: Homepage, https://github.com/MutaharChalmers/catadjust
Author-email: Mutahar Chalmers <mutahar.chalmers@gmail.com>
License: MIT License
License-File: LICENSE
Classifier: Development Status :: 4 - Beta
Classifier: Intended Audience :: Science/Research
Classifier: License :: OSI Approved :: MIT License
Classifier: Operating System :: OS Independent
Classifier: Programming Language :: Python :: 3
Classifier: Topic :: Scientific/Engineering :: GIS
Requires-Python: >=3.12
Requires-Dist: numpy>=1.26.4
Requires-Dist: pandas>=2.0
Requires-Dist: scipy>=1.14.0
Requires-Dist: tqdm>=4.66.1
